jupyteranalytics/__init__.py
jupyteranalytics/extension.py
jupyteranalytics/version.py
jupyteranalytics/static/main.js
jupyteranalytics-1.1.data/data/etc/jupyter/jupyter_notebook_config.d/jupyteranalytics.json
jupyteranalytics-1.1.data/data/etc/jupyter/nbconfig/common.json
jupyteranalytics-1.1.data/data/share/jupyter/nbextensions/jupyteranalytics/main.js
jupyteranalytics-1.1.dist-info/LICENSE.txt
jupyteranalytics-1.1.dist-info/METADATA
jupyteranalytics-1.1.dist-info/WHEEL
jupyteranalytics-1.1.dist-info/top_level.txt
jupyteranalytics-1.1.dist-info/RECORD
