Metadata-Version: 2.1
Name: jupyteranalytics
Version: 1.1
Summary: Adds Google Analytics to Jupyter notebooks
Home-page: UNKNOWN
Author: PingThings, Inc.
Author-email: support@pingthings.io
Maintainer: PingThings, Inc.
Maintainer-email: support@pingthings.io
License: BSD-3-Clause
Download-URL: https://github.com/PingThingsIO/jupyter-analytics/tarball/v1.1
Project-URL: Download, https://github.com/PingThingsIO/jupyter-analytics/tarball/v1.1
Project-URL: Source, https://github.com/PingThingsIO/jupyter-analytics
Project-URL: Tracker, https://github.com/PingThingsIO/jupyter-analytics/issues
Keywords: Google Analytics,notebooks,Jupyter,JupyterHub
Platform: UNKNOWN
Classifier: Development Status :: 4 - Beta
Classifier: Environment :: Web Environment
Classifier: Framework :: Jupyter
Classifier: Intended Audience :: Developers
Classifier: Intended Audience :: Science/Research
Classifier: Intended Audience :: System Administrators
Classifier: License :: OSI Approved :: BSD License
Classifier: Natural Language :: English
Classifier: Operating System :: OS Independent
Classifier: Programming Language :: Python
Requires-Python: >=3.4, <4
Requires-Dist: notebook (>=5.3)
